raion/__init__.py
raion/cli/__init__.py
raion/cli/application.py
raion/commands/KeyGenerate.py
raion/commands/Os.py
raion/commands/Serve.py
raion/commands/__init__.py
raion/core/__init__.py
raion/core/application.py
raion/core/logging.py
raion/core/paths.py
raion/routing/Route.py
raion/routing/Routing.py
raion/routing/__init__.py
raion-0.1.7.dist-info/entry_points.txt
raion-0.1.7.dist-info/WHEEL
raion-0.1.7.dist-info/METADATA
raion-0.1.7.dist-info/RECORD
