Metadata-Version: 2.1
Name: raion
Version: 0.1.7
Summary: Rion Framework
Author: Raion
Author-email: framework@raion.dev
Requires-Python: >=3.9,<4.0
Classifier: Programming Language :: Python :: 3
Classifier: Programming Language :: Python :: 3.9
Requires-Dist: fastapi[all] (>=0.65.2,<0.66.0)
Requires-Dist: typer[all] (>=0.3.2,<0.4.0)
